bisslog_flask/__init__.py
bisslog_flask/builder/__init__.py
bisslog_flask/builder/builder_flask_app_manager.py
bisslog_flask/builder/static_python_construct_data.py
bisslog_flask/cli/__init__.py
bisslog_flask/cli/commands/__init__.py
bisslog_flask/cli/commands/build.py
bisslog_flask/cli/commands/run.py
bisslog_flask/initializer/__init__.py
bisslog_flask/initializer/bisslog_flask_http_resolver.py
bisslog_flask/initializer/bisslog_flask_resolver.py
bisslog_flask/initializer/bisslog_flask_ws_resolver.py
bisslog_flask/initializer/init_flask_app_manager.py
bisslog_flask/socket_helper/__init__.py
bisslog_flask/socket_helper/socket_helper.py
bisslog_flask-0.0.3.dist-info/licenses/LICENSE
bisslog_flask-0.0.3.dist-info/METADATA
bisslog_flask-0.0.3.dist-info/WHEEL
bisslog_flask-0.0.3.dist-info/entry_points.txt
bisslog_flask-0.0.3.dist-info/top_level.txt
bisslog_flask-0.0.3.dist-info/RECORD
