Metadata-Version: 2.4
Name: bisslog_flask
Version: 0.0.3
Summary: It is an extension of the bisslog library to support processes with flask
Author-email: Darwin Stiven Herrera Cartagena <darwinsherrerac@gmail.com>
Project-URL: Homepage, https://github.com/darwinhc/bisslog-flask
Keywords: hexagonal,adapters,bisslog,flask
Classifier: Programming Language :: Python :: 3
Classifier: Operating System :: OS Independent
Requires-Python: >=3.7
License-File: LICENSE
Requires-Dist: bisslog>=0.0.9
Requires-Dist: bisslog-schema>=0.0.10
Requires-Dist: flask
Provides-Extra: websocket
Requires-Dist: flask-socketio; extra == "websocket"
Provides-Extra: cors
Requires-Dist: flask-cors>=6.0.0; extra == "cors"
Provides-Extra: async
Requires-Dist: Flask[async]>=2.2; extra == "async"
Dynamic: license-file
